disease_ontology/__init__.py
disease_ontology/bin/__init__.py
disease_ontology/bin/main.py
disease_ontology/data/DO.pkl
disease_ontology/util/__init__.py
disease_ontology/util/fuzzy_query.py
disease_ontology/util/obo.py
disease_ontology/version/version.json
disease_ontology-1.0.1.dist-info/METADATA
disease_ontology-1.0.1.dist-info/WHEEL
disease_ontology-1.0.1.dist-info/entry_points.txt
disease_ontology-1.0.1.dist-info/top_level.txt
disease_ontology-1.0.1.dist-info/RECORD
